[
    {
        "id": "1",
        "name": "JavaScript Drum Kit",
        "description": "Play the drums with key-events!"
    },
    {
        "id": "2",
        "name": "JS and CSS Clock",
        "description": "Simple analog clock with transforms"
    },
    {
        "id": "3",
        "name": "CSS Variables",
        "description": "How to change CSS variables"
    },
    {
        "id": "4",
        "name": "Array Cardio Day 1",
        "description": "Basic and practical exercises with Arrays"
    },
    {
        "id": "5",
        "name": "Flex Panel Gallery",
        "description": "A simple but elegant flex-gallery "
    },
    {
        "id": "6",
        "name": "Type Ahead",
        "description": "Intuitive data search with a twist"
    },
    {
        "id": "7",
        "name": "Array Cardio Day 2",
        "description": "Basic and practical exercises with Arrays (II)"
    },
    {
        "id": "8",
        "name": "Fun with HTML5 Canvas",
        "description": "todo..."
    },
    {
        "id": "9",
        "name": "Dev Tools Domination",
        "description": "todo..."
    },
    {
        "id": "10",
        "name": "Hold Shift and Check Checkboxes",
        "description": "todo..."
    },
    {
        "id": "11",
        "name": "Custom Video Player",
        "description": "todo..."
    },
    {
        "id": "12",
        "name": "Key Sequence Detection",
        "description": "todo..."
    },
    {
        "id": "13",
        "name": "Slide in on Scroll",
        "description": "todo..."
    },
    {
        "id": "14",
        "name": "JavaScript References VS Copying",
        "description": "todo..."
    },
    {
        "id": "15",
        "name": "LocalStorage",
        "description": "todo..."
    },
    {
        "id": "16",
        "name": "Mouse Move Shadow",
        "description": "todo..."
    },
    {
        "id": "17",
        "name": "Sort Without Articles",
        "description": "todo..."
    },
    {
        "id": "18",
        "name": "Adding Up Times with Reduce",
        "description": "todo..."
    },
    {
        "id": "19",
        "name": "Webcam Fun",
        "description": "todo..."
    },
    {
        "id": "20",
        "name": "Speech Detection",
        "description": "todo..."
    },
    {
        "id": "21",
        "name": "Geolocation",
        "description": "todo..."
    },
    {
        "id": "22",
        "name": "Follow Along Link Highlighter",
        "description": "todo..."
    },
    {
        "id": "23",
        "name": "Speech Synthesis",
        "description": "todo..."
    },
    {
        "id": "24",
        "name": "Sticky Nav",
        "description": "todo..."
    },
    {
        "id": "25",
        "name": "Event Capture, Propagation, Bubbling and Once",
        "description": "todo..."
    },
    {
        "id": "26",
        "name": "Stripe Follow Along Nav",
        "description": "todo..."
    },
    {
        "id": "27",
        "name": "Click and Drag",
        "description": "todo..."
    },
    {
        "id": "28",
        "name": "Video Speed Controller",
        "description": "todo..."
    },
    {
        "id": "29",
        "name": "Countdown Timer",
        "description": "todo..."
    },
    {
        "id": "30",
        "name": "Whack A Mole",
        "description": "todo..."
    }
]
